houdini_package_runner/__init__.py
houdini_package_runner/config.py
houdini_package_runner/parser.py
houdini_package_runner/runners.toml
houdini_package_runner/utils.py
houdini_package_runner/discoverers/__init__.py
houdini_package_runner/discoverers/base.py
houdini_package_runner/discoverers/package.py
houdini_package_runner/items/__init__.py
houdini_package_runner/items/base.py
houdini_package_runner/items/dialog_script.py
houdini_package_runner/items/digital_asset.py
houdini_package_runner/items/filesystem.py
houdini_package_runner/items/xml.py
houdini_package_runner/runners/__init__.py
houdini_package_runner/runners/base.py
houdini_package_runner/runners/utils.py
houdini_package_runner/runners/black/__init__.py
houdini_package_runner/runners/black/runner.py
houdini_package_runner/runners/flake8/__init__.py
houdini_package_runner/runners/flake8/runner.py
houdini_package_runner/runners/isort/__init__.py
houdini_package_runner/runners/isort/isort.cfg
houdini_package_runner/runners/isort/runner.py
houdini_package_runner/runners/modernize/__init__.py
houdini_package_runner/runners/modernize/runner.py
houdini_package_runner/runners/pylint/__init__.py
houdini_package_runner/runners/pylint/runner.py
houdini_package_runner-0.4.1.dist-info/LICENSE
houdini_package_runner-0.4.1.dist-info/METADATA
houdini_package_runner-0.4.1.dist-info/WHEEL
houdini_package_runner-0.4.1.dist-info/entry_points.txt
houdini_package_runner-0.4.1.dist-info/top_level.txt
houdini_package_runner-0.4.1.dist-info/RECORD
