Metadata-Version: 2.1
Name: houdini-package-runner
Version: 0.4.1
Summary: Tooling to analyze or perform actions on Python code in Houdini packages
Home-page: https://github.com/captainhammy/houdini_package_runner
Author: Graham Thompson
Author-email: captainhammy@gmail.com
License: MIT
Classifier: License :: OSI Approved :: MIT License
Classifier: Operating System :: MacOS
Classifier: Operating System :: Microsoft :: Windows
Classifier: Operating System :: Unix
Classifier: Programming Language :: Python
Classifier: Programming Language :: Python :: 3 :: Only
Classifier: Programming Language :: Python :: 3.7
Classifier: Programming Language :: Python :: 3.8
Classifier: Programming Language :: Python :: 3.9
Classifier: Programming Language :: Python :: 3.10
Classifier: Topic :: Scientific/Engineering :: Information Analysis
Classifier: Topic :: Software Development :: Testing
Classifier: Topic :: Utilities
Requires-Python: >=3.7.0
License-File: LICENSE
Requires-Dist: black
Requires-Dist: deepmerge
Requires-Dist: flake8
Requires-Dist: isort
Requires-Dist: lxml
Requires-Dist: modernize
Requires-Dist: pylint
Requires-Dist: pyparsing
Requires-Dist: termcolor
Requires-Dist: toml
Provides-Extra: test
Requires-Dist: pytest ; extra == 'test'
Requires-Dist: pytest-cov ; extra == 'test'
Requires-Dist: pytest-datadir ; extra == 'test'
Requires-Dist: pytest-mock ; extra == 'test'
Requires-Dist: pytest-subprocess ; extra == 'test'
Requires-Dist: tox ; extra == 'test'
